irt_test/__init__.py
irt_test/irt.py
irt_test-0.1.2.dist-info/LICENSE
irt_test-0.1.2.dist-info/METADATA
irt_test-0.1.2.dist-info/WHEEL
irt_test-0.1.2.dist-info/RECORD
